__init__.py
AICelltype/__init__.py
AICelltype-0.0.6.dist-info/LICENSE
AICelltype-0.0.6.dist-info/METADATA
AICelltype-0.0.6.dist-info/WHEEL
AICelltype-0.0.6.dist-info/top_level.txt
AICelltype-0.0.6.dist-info/RECORD
