Metadata-Version: 2.1
Name: AICelltype
Version: 0.0.6
Summary: AICelltype: Annotate cell type through gpt-4 without openai key.
Author-email: renzhg <rzgedu@163.com>
Classifier: Programming Language :: Python :: 3
Classifier: License :: OSI Approved :: MIT License
Classifier: Operating System :: OS Independent
Requires-Python: >=3.10.0
License-File: LICENSE
Requires-Dist: dashscope ==1.17.1
Requires-Dist: requests ==2.31.0
